{
    "mapSize": 4,
    "objects": [
        {
            "type": "player",
            "id": "1234",
            "xy": {
                "x": 1,
                "y": 1
            },
            "model": {
                "name": "SomeName",
                "color": "blue",
                "health": 100
            }
        },
        {
            "type": "coin",
            "id": "1",
            "xy": {
                "x": 1,
                "y": 2
            }
        }
    ],
    "events": [
        {
            "type": "pickCoin",
            "id": "1234",
            "target": "1",
			"update": {"1234": {"coin": 10}}
        }
    ]
}
